{"id":"008769d63eeb68ce07734348dc32e710ee48115c","url":"https://www.brandbrahma.com/","title":"BrandBrahma – Agentic AI Platform to Discover, Build & Scale Ventures","site_name":"Buzzing","source":"www.brandbrahma.com","byline":null,"excerpt":"BrandBrahma is an agentic AI platform from India that helps you discover, build, launch, and scale ventures using intelligent AI tools, automation, and digital asset solutions.","content_html":"<DIV class=\"page\" id=\"readability-page-1\"><div data-widget_type=\"html.default\" data-id=\"35aeae3\" data-element_type=\"container\" data-e-type=\"container\" data-settings=\"{&quot;thegem_container_layout&quot;:&quot;elementor&quot;}\">\n\t\t\t\t\t\n<html lang=\"en\">\n<head>\n<meta charset=\"UTF-8\">\n<meta name=\"viewport\" content=\"width=device-width, initial-scale=1.0\">\n<title>BrandBrahma — AI Domain Lister Section</title>\n\n\n\n\n<!-- ════════════════════════════════════════\n     URLS CONFIG — edit here only\n════════════════════════════════════════ -->\n\n\n<!-- ════════════════════════════════════════\n     MARKUP\n════════════════════════════════════════ -->\n<section id=\"bbail\" aria-labelledby=\"bbail-h1\">\n\n  <!-- ══ HERO ══ -->\n  <div>\n\n        <!-- Left copy -->\n        <div>\n          <p><span></span>\n            AI-Powered Domain Marketplace OS\n          </p>\n          <h2 id=\"bbail-h1\">\n            List Your Domain.<br>\n            Let <span>AI</span> Build<br>\n            Your <span>Listing</span>.\n          </h2>\n          <p>\n            Enter your domain — our AI OS writes the <strong>title, description, FAQs, SEO meta, tags</strong>\n            and even generates a <strong>wordmark</strong>. Your listing goes live in minutes, not days.\n          </p>\n          <P>\n            <a href=\"https://www.brandbrahma.com/sell-your-domain/\">\n              List My Domain Free\n              <svg viewBox=\"0 0 24 24\"><line x1=\"5\" y1=\"12\" x2=\"19\" y2=\"12\" /><polyline points=\"12 5 19 12 12 19\" /></svg>\n            </a>\n            <a href=\"https://www.brandbrahma.com/marketplace/\">\n              Browse Marketplace\n              <svg viewBox=\"0 0 24 24\"><circle cx=\"11\" cy=\"11\" r=\"8\" /><line x1=\"21\" y1=\"21\" x2=\"16.65\" y2=\"16.65\" /></svg>\n            </a>\n          </P>\n        </div>\n\n        <!-- Right — AI preview demo card -->\n        <div>\n          <p><span>AI Domain Preview — Free, No Login</span></p>\n          <div>\n            <p><span>Domain</span>\n              <span id=\"bbail-out-domain\">velox.ai</span>\n            </p>\n            <p><span>AI-Generated Title</span>\n              <span id=\"bbail-out-title\">Velox.ai — Premium AI Brand Domain for Next-Gen Startups</span>\n            </p>\n            <p><span>Short Description</span>\n              <span id=\"bbail-out-desc\">A crisp, fast-sounding domain perfect for AI tooling, automation, or SaaS. Instant brand authority with a .ai extension.</span>\n            </p>\n            <div>\n              <p><span>Suggested Tags</span></p><p><span>AI</span>\n                <span>SaaS</span>\n                <span>Automation</span>\n                <span>Startup</span>\n                <span>Tech</span>\n              </p>\n            </div>\n          </div>\n          <p><span>\n            <svg viewBox=\"0 0 24 24\"><polyline points=\"20 6 9 17 4 12\" /></svg>\n            Free preview · No login required\n          </span>\n        </p></div>\n\n      </div>\n\n  <!-- ══ FEATURES ══ -->\n  <div>\n      <div>\n          <p><span>AI Domain Lister OS · v2.2</span></p><h2>Everything AI Builds for You</h2>\n          <p>Six intelligent tools that turn a domain name into a complete, sale-ready product page.</p>\n        </div>\n      <div>\n\n        <div>\n          \n          <p><span>Free</span></p>\n          <p><span>AI Preview</span></p><p>Get an instant AI-generated title, short description and tag preview for any domain — free, with no login. See your listing's potential before committing.</p>\n        </div>\n\n        <div>\n          \n          <p><span>AI</span></p>\n          <p><span>AI Page Builder</span></p><p>One click generates a full product page: long-form description, buyer FAQs, keyword tags, SEO meta title and meta description — all field-by-field regeneratable.</p>\n        </div>\n\n        <div>\n          \n          <p><span>New</span></p>\n          <p><span>AI Wordmark Generator</span></p><p>Automatically creates a styled SVG wordmark for your domain in dark or light variants — saved and attached to your listing as a downloadable brand asset.</p>\n        </div>\n\n        <div>\n          \n          <p><span>SEO</span></p>\n          <p><span>AI SEO Optimiser</span></p><p>Generates a Yoast- and RankMath-ready meta title (≤60 chars) and meta description (≤155 chars). Auto-written to rank for domain-related buyer searches.</p>\n        </div>\n\n        <div>\n          \n          <p><span>Dashboard</span></p>\n          <p><span>Seller Dashboard</span></p><p>Full-featured dashboard with listings, orders, earnings and credit management. Approve, edit or republish listings. Track buyer inquiries in one place.</p>\n        </div>\n\n        <div>\n          \n          <p><span>Seamless</span></p>\n          <p><span>Smart Checkout + OTP</span></p><p>Custom modal checkout with 5 payment methods, email OTP verification and buyer questionnaire — bypassing WooCommerce defaults for a frictionless buyer experience.</p>\n        </div>\n\n      </div>\n    </div>\n\n  <!-- ══ HOW IT WORKS ══ -->\n  <div>\n      <div>\n        <p><span>How It Works</span></p><h2>From Domain to Live Listing in 4 Steps</h2>\n        <p>No design skills, no copywriting, no SEO expertise needed. Just your domain name.</p>\n      </div>\n      <div>\n\n        <div>\n          <p>1</p>\n          <p><span>Enter Your Domain</span></p><p>Type your domain name into the AI previewer. Get an instant free preview — title, tags, and short description — no account needed.</p>\n          <p><span>Free · No login</span>\n        </p></div>\n\n        <div>\n          <p>2</p>\n          <p><span>AI Builds Your Page</span></p><p>Log in and continue to the AI Builder. It generates your full listing page: long description, FAQs, SEO meta, keyword tags — all editable field by field.</p>\n          <p><span>AI-Powered</span>\n        </p></div>\n\n        <div>\n          <p>3</p>\n          <p><span>Review &amp; Publish</span></p><p>Review, tweak or regenerate any field. One-click publish pushes your listing live to the BrandBrahma marketplace with SEO tags applied automatically.</p>\n          <p><span>5 Credits</span>\n        </p></div>\n\n        <div>\n          <p>4</p>\n          <p><span>Sell &amp; Get Paid</span></p><p>Buyers find you via search. They complete checkout with OTP verification across 5 payment methods. You track earnings in your seller dashboard.</p>\n          <p><span>You Get Paid</span>\n        </p></div>\n\n      </div>\n    </div>\n\n  <!-- ══ CATEGORY CAROUSEL ══ -->\n  <div>\n          <p><span>Browse the Marketplace</span></p><h2>7 Curated Categories</h2>\n        </div>\n\n  <!-- ══ STATS BAR ══ -->\n  <div>\n        <p><span>500<span>+</span></span>\n          <span>Curated Domains</span>\n        </p>\n        <p><span>50<span>K+</span></span>\n          <span>Happy Founders</span>\n        </p>\n        <p><span>4.9<span>★</span></span>\n          <span>Average Rating</span>\n        </p>\n        <p><span>5<span>min</span></span>\n          <span>Avg. Listing Time</span>\n        </p>\n      </div>\n\n  <!-- ══ SELLER + BROWSE CTA ══ -->\n  <div>\n          <p><span>AI Domain Marketplace · List in 5 Minutes</span></p><h2>Your domain deserves<br>a <em>buyer who values it</em>.</h2>\n          <p>\n            Stop letting premium domains sit idle. BrandBrahma's AI writes your entire listing — title, description,\n            FAQs, SEO tags and wordmark — then puts it in front of 50,000+ founders actively looking for their next brand.\n          </p>\n          <p><span><svg viewBox=\"0 0 24 24\"><polyline points=\"20 6 9 17 4 12\" /></svg>Free AI preview, no login</span>\n            <span><svg viewBox=\"0 0 24 24\"><polyline points=\"20 6 9 17 4 12\" /></svg>AI title, desc, FAQs &amp; SEO</span>\n            <span><svg viewBox=\"0 0 24 24\"><polyline points=\"20 6 9 17 4 12\" /></svg>AI Wordmark generated</span>\n            <span><svg viewBox=\"0 0 24 24\"><polyline points=\"20 6 9 17 4 12\" /></svg>5 payment methods</span>\n            <span><svg viewBox=\"0 0 24 24\"><polyline points=\"20 6 9 17 4 12\" /></svg>OTP-verified checkout</span>\n            <span><svg viewBox=\"0 0 24 24\"><polyline points=\"20 6 9 17 4 12\" /></svg>Seller dashboard &amp; earnings</span>\n          </p>\n        </div>\n\n</section>\n\n\n</head></html>\n\t\t\t\t</div></DIV>","content_text":"BrandBrahma — AI Domain Lister Section AI-Powered Domain Marketplace OS List Your Domain. Let AI Build Your Listing. Enter your domain — our AI OS writes the title, description, FAQs, SEO meta, tags and even generates a wordmark. Your listing goes live in minutes, not days. List My Domain Free Browse Marketplace AI Domain Preview — Free, No Login Domain velox.ai AI-Generated Title Velox.ai — Premium AI Brand Domain for Next-Gen Startups Short Description A crisp, fast-sounding domain perfect for AI tooling, automation, or SaaS. Instant brand authority with a .ai extension. Suggested TagsAI SaaS Automation Startup Tech Free preview · No login required AI Domain Lister OS · v2.2Everything AI Builds for You Six intelligent tools that turn a domain name into a complete, sale-ready product page. Free AI PreviewGet an instant AI-generated title, short description and tag preview for any domain — free, with no login. See your listing's potential before committing. AI AI Page BuilderOne click generates a full product page: long-form description, buyer FAQs, keyword tags, SEO meta title and meta description — all field-by-field regeneratable. New AI Wordmark GeneratorAutomatically creates a styled SVG wordmark for your domain in dark or light variants — saved and attached to your listing as a downloadable brand asset. SEO AI SEO OptimiserGenerates a Yoast- and RankMath-ready meta title (≤60 chars) and meta description (≤155 chars). Auto-written to rank for domain-related buyer searches. Dashboard Seller DashboardFull-featured dashboard with listings, orders, earnings and credit management. Approve, edit or republish listings. Track buyer inquiries in one place. Seamless Smart Checkout + OTPCustom modal checkout with 5 payment methods, email OTP verification and buyer questionnaire — bypassing WooCommerce defaults for a frictionless buyer experience. How It WorksFrom Domain to Live Listing in 4 Steps No design skills, no copywriting, no SEO expertise needed. Just your domain name. 1 Enter Your DomainType your domain name into the AI previewer. Get an instant free preview — title, tags, and short description — no account needed. Free · No login 2 AI Builds Your PageLog in and continue to the AI Builder. It generates your full listing page: long description, FAQs, SEO meta, keyword tags — all editable field by field. AI-Powered 3 Review & PublishReview, tweak or regenerate any field. One-click publish pushes your listing live to the BrandBrahma marketplace with SEO tags applied automatically. 5 Credits 4 Sell & Get PaidBuyers find you via search. They complete checkout with OTP verification across 5 payment methods. You track earnings in your seller dashboard. You Get Paid Browse the Marketplace7 Curated Categories 500+ Curated Domains 50K+ Happy Founders 4.9★ Average Rating 5min Avg. Listing Time AI Domain Marketplace · List in 5 MinutesYour domain deservesa buyer who values it. Stop letting premium domains sit idle. BrandBrahma's AI writes your entire listing — title, description, FAQs, SEO tags and wordmark — then puts it in front of 50,000+ founders actively looking for their next brand. Free AI preview, no login AI title, desc, FAQs & SEO AI Wordmark generated 5 payment methods OTP-verified checkout Seller dashboard & earnings","fetched_at":"2026-07-24T05:07:58.855Z","ok":true,"blocks":[{"html_en":"<p><span></span>\n            AI-Powered Domain Marketplace OS\n          </p>","sentences":[{"en":"AI-Powered Domain Marketplace OS","zh":"人工智能驱动的域名市场操作系统"}]},{"html_en":"<h2 id=\"bbail-h1\">\n            List Your Domain.<br>\n            Let <span>AI</span> Build<br>\n            Your <span>Listing</span>.\n          </h2>","sentences":[{"en":"List Your Domain.","zh":"列出您的域。"},{"en":"Let AI Build Your Listing.","zh":"让人工智能构建您的列表。"}]},{"html_en":"<p>\n            Enter your domain — our AI OS writes the <strong>title, description, FAQs, SEO meta, tags</strong>\n            and even generates a <strong>wordmark</strong>. Your listing goes live in minutes, not days.\n          </p>","sentences":[{"en":"Enter your domain — our AI OS writes the title, description, FAQs, SEO meta, tags and even generates a wordmark.","zh":"输入您的域名 - 我们的人工智能操作系统会写入标题、描述、常见问题解答、SEO 元、标签，甚至生成文字标记。"},{"en":"Your listing goes live in minutes, not days.","zh":"您的列表在几分钟内即可上线，而不是几天。"}]},{"html_en":"<p>\n            <a href=\"https://www.brandbrahma.com/sell-your-domain/\">\n              List My Domain Free\n              <svg viewBox=\"0 0 24 24\"><line x1=\"5\" y1=\"12\" x2=\"19\" y2=\"12\" /><polyline points=\"12 5 19 12 12 19\" /></svg>\n            </a>\n            <a href=\"https://www.brandbrahma.com/marketplace/\">\n              Browse Marketplace\n              <svg viewBox=\"0 0 24 24\"><circle cx=\"11\" cy=\"11\" r=\"8\" /><line x1=\"21\" y1=\"21\" x2=\"16.65\" y2=\"16.65\" /></svg>\n            </a>\n          </p>","sentences":[{"en":"List My Domain Free Browse Marketplace","zh":"列出我的域名 免费浏览市场"}]},{"html_en":"<p><span>AI Domain Preview — Free, No Login</span></p>","sentences":[{"en":"AI Domain Preview — Free, No Login","zh":"AI 域预览 — 免费，无需登录"}]},{"html_en":"<p><span>Domain</span>\n              <span id=\"bbail-out-domain\">velox.ai</span>\n            </p>","sentences":[{"en":"Domain velox.ai","zh":"域名 velox.ai"}]},{"html_en":"<p><span>AI-Generated Title</span>\n              <span id=\"bbail-out-title\">Velox.ai — Premium AI Brand Domain for Next-Gen Startups</span>\n            </p>","sentences":[{"en":"AI-Generated Title Velox.ai — Premium AI Brand Domain for Next-Gen Startups","zh":"AI 生成的标题 Velox.ai — 面向下一代初创公司的优质 AI 品牌域名"}]},{"html_en":"<p><span>Short Description</span>\n              <span id=\"bbail-out-desc\">A crisp, fast-sounding domain perfect for AI tooling, automation, or SaaS. Instant brand authority with a .ai extension.</span>\n            </p>","sentences":[{"en":"Short Description A crisp, fast-sounding domain perfect for AI tooling, automation, or SaaS.","zh":"简短描述 一个清晰、快速的领域，非常适合人工智能工具、自动化或 SaaS。"},{"en":"Instant brand authority with a .ai extension.","zh":"通过 .ai 扩展名即时获得品牌权威。"}]},{"html_en":"<p><span>Suggested Tags</span></p>","sentences":[{"en":"Suggested Tags","zh":"建议标签"}]},{"html_en":"<p><span>AI</span>\n                <span>SaaS</span>\n                <span>Automation</span>\n                <span>Startup</span>\n                <span>Tech</span>\n              </p>","sentences":[{"en":"AI SaaS Automation Startup Tech","zh":"AI SaaS 自动化初创公司技术"}]},{"html_en":"<p><span>\n            <svg viewBox=\"0 0 24 24\"><polyline points=\"20 6 9 17 4 12\" /></svg>\n            Free preview · No login required\n          </span>\n        </p>","sentences":[{"en":"Free preview · No login required","zh":"免费预览·无需登录"}]},{"html_en":"<p><span>AI Domain Lister OS · v2.2</span></p>","sentences":[{"en":"AI Domain Lister OS · v2.2","zh":"AI域列表器操作系统v2.2"}]},{"html_en":"<h2>Everything AI Builds for You</h2>","sentences":[{"en":"Everything AI Builds for You","zh":"人工智能为您打造的一切"}]},{"html_en":"<p>Six intelligent tools that turn a domain name into a complete, sale-ready product page.</p>","sentences":[{"en":"Six intelligent tools that turn a domain name into a complete, sale-ready product page.","zh":"六种智能工具可将域名转变为完整的、可销售的产品页面。"}]},{"html_en":"<p><span>Free</span></p>","sentences":[]},{"html_en":"<p><span>AI Preview</span></p>","sentences":[{"en":"AI Preview","zh":"人工智能预览"}]},{"html_en":"<p>Get an instant AI-generated title, short description and tag preview for any domain — free, with no login. See your listing's potential before committing.</p>","sentences":[{"en":"Get an instant AI-generated title, short description and tag preview for any domain — free, with no login.","zh":"获取任何域的人工智能即时生成的标题、简短描述和标签预览——免费，无需登录。"},{"en":"See your listing's potential before committing.","zh":"在做出承诺之前先了解您的列表的潜力。"}]},{"html_en":"<p><span>AI</span></p>","sentences":[]},{"html_en":"<p><span>AI Page Builder</span></p>","sentences":[{"en":"AI Page Builder","zh":"人工智能页面生成器"}]},{"html_en":"<p>One click generates a full product page: long-form description, buyer FAQs, keyword tags, SEO meta title and meta description — all field-by-field regeneratable.</p>","sentences":[{"en":"One click generates a full product page: long-form description, buyer FAQs, keyword tags, SEO meta title and meta description — all field-by-field regeneratable.","zh":"一键生成完整的产品页面：长格式描述、买家常见问题解答、关键字标签、SEO 元标题和元描述 - 所有这些都可以逐个字段重新生成。"}]},{"html_en":"<p><span>New</span></p>","sentences":[]},{"html_en":"<p><span>AI Wordmark Generator</span></p>","sentences":[{"en":"AI Wordmark Generator","zh":"人工智能字标生成器"}]},{"html_en":"<p>Automatically creates a styled SVG wordmark for your domain in dark or light variants — saved and attached to your listing as a downloadable brand asset.</p>","sentences":[{"en":"Automatically creates a styled SVG wordmark for your domain in dark or light variants — saved and attached to your listing as a downloadable brand asset.","zh":"自动为您的域名创建深色或浅色变体的 SVG 文字标记 — 将其作为可下载的品牌资产保存并附加到您的列表中。"}]},{"html_en":"<p><span>SEO</span></p>","sentences":[]},{"html_en":"<p><span>AI SEO Optimiser</span></p>","sentences":[{"en":"AI SEO Optimiser","zh":"人工智能SEO优化"}]},{"html_en":"<p>Generates a Yoast- and RankMath-ready meta title (≤60 chars) and meta description (≤155 chars). Auto-written to rank for domain-related buyer searches.</p>","sentences":[{"en":"Generates a Yoast- and RankMath-ready meta title (≤60 chars) and meta description (≤155 chars).","zh":"生成 Yoast 和 RankMath 就绪的元标题（≤60 个字符）和元描述（≤155 个字符）。"},{"en":"Auto-written to rank for domain-related buyer searches.","zh":"自动编写以对与域相关的买家搜索进行排名。"}]},{"html_en":"<p><span>Dashboard</span></p>","sentences":[{"en":"Dashboard","zh":"仪表板"}]},{"html_en":"<p><span>Seller Dashboard</span></p>","sentences":[{"en":"Seller Dashboard","zh":"卖家仪表板"}]},{"html_en":"<p>Full-featured dashboard with listings, orders, earnings and credit management. Approve, edit or republish listings. Track buyer inquiries in one place.</p>","sentences":[{"en":"Full-featured dashboard with listings, orders, earnings and credit management.","zh":"功能齐全的仪表板，包含列表、订单、收益和信用管理。"},{"en":"Approve, edit or republish listings.","zh":"批准、编辑或重新发布列表。"},{"en":"Track buyer inquiries in one place.","zh":"在一处跟踪买家询问。"}]},{"html_en":"<p><span>Seamless</span></p>","sentences":[{"en":"Seamless","zh":"无缝的"}]},{"html_en":"<p><span>Smart Checkout + OTP</span></p>","sentences":[{"en":"Smart Checkout + OTP","zh":"智能结帐+OTP"}]},{"html_en":"<p>Custom modal checkout with 5 payment methods, email OTP verification and buyer questionnaire — bypassing WooCommerce defaults for a frictionless buyer experience.</p>","sentences":[{"en":"Custom modal checkout with 5 payment methods, email OTP verification and buyer questionnaire — bypassing WooCommerce defaults for a frictionless buyer experience.","zh":"具有 5 种付款方式的自定义模式结帐、电子邮件 OTP 验证和买家调查问卷 — 绕过 WooCommerce 默认设置，提供无摩擦的买家体验。"}]},{"html_en":"<p><span>How It Works</span></p>","sentences":[{"en":"How It Works","zh":"它是如何运作的"}]},{"html_en":"<h2>From Domain to Live Listing in 4 Steps</h2>","sentences":[{"en":"From Domain to Live Listing in 4 Steps","zh":"只需 4 步即可从域名到实时列表"}]},{"html_en":"<p>No design skills, no copywriting, no SEO expertise needed. Just your domain name.</p>","sentences":[{"en":"No design skills, no copywriting, no SEO expertise needed.","zh":"无需设计技能，无需文案，无需 SEO 专业知识。"},{"en":"Just your domain name.","zh":"只是您的域名。"}]},{"html_en":"<p><span>Enter Your Domain</span></p>","sentences":[{"en":"Enter Your Domain","zh":"输入您的域名"}]},{"html_en":"<p>Type your domain name into the AI previewer. Get an instant free preview — title, tags, and short description — no account needed.</p>","sentences":[{"en":"Type your domain name into the AI previewer.","zh":"在 AI 预览器中输入您的域名。"},{"en":"Get an instant free preview — title, tags, and short description — no account needed.","zh":"获得即时免费预览 - 标题、标签和简短描述 - 无需帐户。"}]},{"html_en":"<p><span>Free · No login</span>\n        </p>","sentences":[{"en":"Free · No login","zh":"免费·无需登录"}]},{"html_en":"<p><span>AI Builds Your Page</span></p>","sentences":[{"en":"AI Builds Your Page","zh":"人工智能构建您的页面"}]},{"html_en":"<p>Log in and continue to the AI Builder. It generates your full listing page: long description, FAQs, SEO meta, keyword tags — all editable field by field.</p>","sentences":[{"en":"Log in and continue to the AI Builder.","zh":"登录并继续访问 AI Builder。"},{"en":"It generates your full listing page: long description, FAQs, SEO meta, keyword tags — all editable field by field.","zh":"它会生成完整的列表页面：详细描述、常见问题解答、SEO 元、关键字标签 - 所有这些都可以逐个字段进行编辑。"}]},{"html_en":"<p><span>AI-Powered</span>\n        </p>","sentences":[{"en":"AI-Powered","zh":"人工智能驱动"}]},{"html_en":"<p><span>Review &amp; Publish</span></p>","sentences":[{"en":"Review & Publish","zh":"审核并发布"}]},{"html_en":"<p>Review, tweak or regenerate any field. One-click publish pushes your listing live to the BrandBrahma marketplace with SEO tags applied automatically.</p>","sentences":[{"en":"Review, tweak or regenerate any field.","zh":"检查、调整或重新生成任何字段。"},{"en":"One-click publish pushes your listing live to the BrandBrahma marketplace with SEO tags applied automatically.","zh":"一键发布将您的列表推送到 BrandBrahma 市场，并自动应用 SEO 标签。"}]},{"html_en":"<p><span>5 Credits</span>\n        </p>","sentences":[{"en":"5 Credits","zh":"5 学分"}]},{"html_en":"<p><span>Sell &amp; Get Paid</span></p>","sentences":[{"en":"Sell & Get Paid","zh":"出售并获得报酬"}]},{"html_en":"<p>Buyers find you via search. They complete checkout with OTP verification across 5 payment methods. You track earnings in your seller dashboard.</p>","sentences":[{"en":"Buyers find you via search.","zh":"买家通过搜索找到您。"},{"en":"They complete checkout with OTP verification across 5 payment methods.","zh":"他们通过 5 种付款方式的 OTP 验证完成结账。"},{"en":"You track earnings in your seller dashboard.","zh":"您可以在卖家仪表板中跟踪收入。"}]},{"html_en":"<p><span>You Get Paid</span>\n        </p>","sentences":[{"en":"You Get Paid","zh":"你得到报酬"}]},{"html_en":"<p><span>Browse the Marketplace</span></p>","sentences":[{"en":"Browse the Marketplace","zh":"浏览市场"}]},{"html_en":"<h2>7 Curated Categories</h2>","sentences":[{"en":"7 Curated Categories","zh":"7 个精选类别"}]},{"html_en":"<p><span>500<span>+</span></span>\n          <span>Curated Domains</span>\n        </p>","sentences":[{"en":"500+ Curated Domains","zh":"500+ 精选域名"}]},{"html_en":"<p><span>50<span>K+</span></span>\n          <span>Happy Founders</span>\n        </p>","sentences":[{"en":"50K+ Happy Founders","zh":"50K+ 快乐创始人"}]},{"html_en":"<p><span>4.9<span>★</span></span>\n          <span>Average Rating</span>\n        </p>","sentences":[{"en":"4.9★ Average Rating","zh":"4.9★ 平均评分"}]},{"html_en":"<p><span>5<span>min</span></span>\n          <span>Avg. Listing Time</span>\n        </p>","sentences":[{"en":"5min Avg.","zh":"5 分钟平均"},{"en":"Listing Time","zh":"上市时间"}]},{"html_en":"<p><span>AI Domain Marketplace · List in 5 Minutes</span></p>","sentences":[{"en":"AI Domain Marketplace · List in 5 Minutes","zh":"AI域名市场·5分钟上架"}]},{"html_en":"<h2>Your domain deserves<br>a <em>buyer who values it</em>.</h2>","sentences":[{"en":"Your domain deservesa buyer who values it.","zh":"您的域名值得买家重视。"}]},{"html_en":"<p>\n            Stop letting premium domains sit idle. BrandBrahma's AI writes your entire listing — title, description,\n            FAQs, SEO tags and wordmark — then puts it in front of 50,000+ founders actively looking for their next brand.\n          </p>","sentences":[{"en":"Stop letting premium domains sit idle.","zh":"停止让优质域名闲置。"},{"en":"BrandBrahma's AI writes your entire listing — title, description, FAQs, SEO tags and wordmark — then puts it in front of 50,000+ founders actively looking for their next brand.","zh":"BrandBrahma 的人工智能会编写您的整个列表 - 标题、描述、常见问题解答、SEO 标签和文字标记 - 然后将其放在 50,000 多名积极寻找下一个品牌的创始人面前。"}]},{"html_en":"<p><span><svg viewBox=\"0 0 24 24\"><polyline points=\"20 6 9 17 4 12\" /></svg>Free AI preview, no login</span>\n            <span><svg viewBox=\"0 0 24 24\"><polyline points=\"20 6 9 17 4 12\" /></svg>AI title, desc, FAQs &amp; SEO</span>\n            <span><svg viewBox=\"0 0 24 24\"><polyline points=\"20 6 9 17 4 12\" /></svg>AI Wordmark generated</span>\n            <span><svg viewBox=\"0 0 24 24\"><polyline points=\"20 6 9 17 4 12\" /></svg>5 payment methods</span>\n            <span><svg viewBox=\"0 0 24 24\"><polyline points=\"20 6 9 17 4 12\" /></svg>OTP-verified checkout</span>\n            <span><svg viewBox=\"0 0 24 24\"><polyline points=\"20 6 9 17 4 12\" /></svg>Seller dashboard &amp; earnings</span>\n          </p>","sentences":[{"en":"Free AI preview, no login AI title, desc, FAQs & SEO AI Wordmark generated 5 payment methods OTP-verified checkout Seller dashboard & earnings","zh":"免费 AI 预览，无需登录 AI 标题、描述、常见问题解答和 SEO AI 文字标记生成 5 种付款方式 OTP 验证结帐 卖家仪表板和收入"}]}],"translated":true,"content_html_zh":"<div class=\"page\" id=\"readability-page-1\"><div data-widget_type=\"html.default\" data-id=\"35aeae3\" data-element_type=\"container\" data-e-type=\"container\" data-settings=\"{&quot;thegem_container_layout&quot;:&quot;elementor&quot;}\">\n\t\t\t\t\t\n<html lang=\"en\">\n<head>\n<meta charset=\"UTF-8\">\n<meta name=\"viewport\" content=\"width=device-width, initial-scale=1.0\">\n<title>BrandBrahma — AI Domain Lister Section</title>\n\n\n\n\n<!-- ════════════════════════════════════════\n     URLS CONFIG — edit here only\n════════════════════════════════════════ -->\n\n\n<!-- ════════════════════════════════════════\n     MARKUP\n════════════════════════════════════════ -->\n<section id=\"bbail\" aria-labelledby=\"bbail-h1\">\n\n  <!-- ══ HERO ══ -->\n  <div>\n\n        <!-- Left copy -->\n        <div>\n          <p>人工智能驱动的域名市场操作系统</p>\n          <h2 id=\"bbail-h1\">列出您的域。 让人工智能构建您的列表。</h2>\n          <p>输入您的域名 - 我们的人工智能操作系统会写入标题、描述、常见问题解答、SEO 元、标签，甚至生成文字标记。 您的列表在几分钟内即可上线，而不是几天。</p>\n          <p>列出我的域名 免费浏览市场</p>\n        </div>\n\n        <!-- Right — AI preview demo card -->\n        <div>\n          <p>AI 域预览 — 免费，无需登录</p>\n          <div>\n            <p>域名 velox.ai</p>\n            <p>AI 生成的标题 Velox.ai — 面向下一代初创公司的优质 AI 品牌域名</p>\n            <p>简短描述 一个清晰、快速的领域，非常适合人工智能工具、自动化或 SaaS。 通过 .ai 扩展名即时获得品牌权威。</p>\n            <div>\n              <p>建议标签</p><p>AI SaaS 自动化初创公司技术</p>\n            </div>\n          </div>\n          <p>免费预览·无需登录</p></div>\n\n      </div>\n\n  <!-- ══ FEATURES ══ -->\n  <div>\n      <div>\n          <p>AI域列表器操作系统v2.2</p><h2>人工智能为您打造的一切</h2>\n          <p>六种智能工具可将域名转变为完整的、可销售的产品页面。</p>\n        </div>\n      <div>\n\n        <div>\n          \n          <p><span>Free</span></p>\n          <p>人工智能预览</p><p>获取任何域的人工智能即时生成的标题、简短描述和标签预览——免费，无需登录。 在做出承诺之前先了解您的列表的潜力。</p>\n        </div>\n\n        <div>\n          \n          <p><span>AI</span></p>\n          <p>人工智能页面生成器</p><p>一键生成完整的产品页面：长格式描述、买家常见问题解答、关键字标签、SEO 元标题和元描述 - 所有这些都可以逐个字段重新生成。</p>\n        </div>\n\n        <div>\n          \n          <p><span>New</span></p>\n          <p>人工智能字标生成器</p><p>自动为您的域名创建深色或浅色变体的 SVG 文字标记 — 将其作为可下载的品牌资产保存并附加到您的列表中。</p>\n        </div>\n\n        <div>\n          \n          <p><span>SEO</span></p>\n          <p>人工智能SEO优化</p><p>生成 Yoast 和 RankMath 就绪的元标题（≤60 个字符）和元描述（≤155 个字符）。 自动编写以对与域相关的买家搜索进行排名。</p>\n        </div>\n\n        <div>\n          \n          <p>仪表板</p>\n          <p>卖家仪表板</p><p>功能齐全的仪表板，包含列表、订单、收益和信用管理。 批准、编辑或重新发布列表。 在一处跟踪买家询问。</p>\n        </div>\n\n        <div>\n          \n          <p>无缝的</p>\n          <p>智能结帐+OTP</p><p>具有 5 种付款方式的自定义模式结帐、电子邮件 OTP 验证和买家调查问卷 — 绕过 WooCommerce 默认设置，提供无摩擦的买家体验。</p>\n        </div>\n\n      </div>\n    </div>\n\n  <!-- ══ HOW IT WORKS ══ -->\n  <div>\n      <div>\n        <p>它是如何运作的</p><h2>只需 4 步即可从域名到实时列表</h2>\n        <p>无需设计技能，无需文案，无需 SEO 专业知识。 只是您的域名。</p>\n      </div>\n      <div>\n\n        <div>\n          <p>1</p>\n          <p>输入您的域名</p><p>在 AI 预览器中输入您的域名。 获得即时免费预览 - 标题、标签和简短描述 - 无需帐户。</p>\n          <p>免费·无需登录</p></div>\n\n        <div>\n          <p>2</p>\n          <p>人工智能构建您的页面</p><p>登录并继续访问 AI Builder。 它会生成完整的列表页面：详细描述、常见问题解答、SEO 元、关键字标签 - 所有这些都可以逐个字段进行编辑。</p>\n          <p>人工智能驱动</p></div>\n\n        <div>\n          <p>3</p>\n          <p>审核并发布</p><p>检查、调整或重新生成任何字段。 一键发布将您的列表推送到 BrandBrahma 市场，并自动应用 SEO 标签。</p>\n          <p>5 学分</p></div>\n\n        <div>\n          <p>4</p>\n          <p>出售并获得报酬</p><p>买家通过搜索找到您。 他们通过 5 种付款方式的 OTP 验证完成结账。 您可以在卖家仪表板中跟踪收入。</p>\n          <p>你得到报酬</p></div>\n\n      </div>\n    </div>\n\n  <!-- ══ CATEGORY CAROUSEL ══ -->\n  <div>\n          <p>浏览市场</p><h2>7 个精选类别</h2>\n        </div>\n\n  <!-- ══ STATS BAR ══ -->\n  <div>\n        <p>500+ 精选域名</p>\n        <p>50K+ 快乐创始人</p>\n        <p>4.9★ 平均评分</p>\n        <p>5 分钟平均 上市时间</p>\n      </div>\n\n  <!-- ══ SELLER + BROWSE CTA ══ -->\n  <div>\n          <p>AI域名市场·5分钟上架</p><h2>您的域名值得买家重视。</h2>\n          <p>停止让优质域名闲置。 BrandBrahma 的人工智能会编写您的整个列表 - 标题、描述、常见问题解答、SEO 标签和文字标记 - 然后将其放在 50,000 多名积极寻找下一个品牌的创始人面前。</p>\n          <p>免费 AI 预览，无需登录 AI 标题、描述、常见问题解答和 SEO AI 文字标记生成 5 种付款方式 OTP 验证结帐 卖家仪表板和收入</p>\n        </div>\n\n</section>\n\n\n</head></html>\n\t\t\t\t</div></div>"}