{"id":"00d972ced01e9d87ccc21c1e8b35012d2eada193","url":"https://www.v2ex.com/t/1229523","title":"AI 短视频火，到底是视频平台的故意导流导致的？还是大家真喜欢看？","site_name":"Info Flow","source":"V2EX (创意工作者社区)","byline":"NeoWalnut","excerpt":"程序员 - @NeoWalnut - 我感觉 AI 短视频质量比抖音短视频还低，完全就是靠夸张剧情来吸引人，只会让人更变得越来越傻。我看到 AI 视频，心里就就会产生莫名的厌恶，然后就会主动跳过。但是现在 AI 短视频那么火，到底","content_html":"<DIV class=\"page\" id=\"readability-page-1\"><div><p>我一直的观点：所有人都不赚钱，跟风白忙活，只有平台赚钱，平台造势，通杀。<br>论据：<br>1 ，抖音平台上，不投放不触达，所以巨量引擎一定是赢家，只有持续买量，才能有增长。<br>2 ，CDN 还需要消耗你一波，内容上线后，平台 CDN package 还得另付费。<br>3 ，seedance 2 的 API 流量费用。大概 4 ～ 5 次抽卡调整确定最终视频。 </p><p>以上都是一家公司赚，一个是声势，二哥是提亮，三个造趋势。</p><p>只要公司跟进，大部分都是亏损的，赚的万八的还不够人力工时投入；以上还没算内容公司人力成本投入；</p><p>所以怎么可能会有人赚钱。</p><p>------------------------- </p><p>短剧没人了，漫剧能顶到什么时候是另一个问题，AI 漫剧～～能不能最后成气候，也要看模型最终的能力。但是都逃不脱以上 123 个论据。</p><p>制造工具平台的，只要不够快吃到第一杯羹或者吃到第一波势头给公司造势拿到投融资之类的，都是死路，只要趋势变了，内容输出平台工具就没意义。</p></div></DIV>","content_text":"我一直的观点：所有人都不赚钱，跟风白忙活，只有平台赚钱，平台造势，通杀。论据：1 ，抖音平台上，不投放不触达，所以巨量引擎一定是赢家，只有持续买量，才能有增长。2 ，CDN 还需要消耗你一波，内容上线后，平台 CDN package 还得另付费。3 ，seedance 2 的 API 流量费用。大概 4 ～ 5 次抽卡调整确定最终视频。 以上都是一家公司赚，一个是声势，二哥是提亮，三个造趋势。只要公司跟进，大部分都是亏损的，赚的万八的还不够人力工时投入；以上还没算内容公司人力成本投入；所以怎么可能会有人赚钱。------------------------- 短剧没人了，漫剧能顶到什么时候是另一个问题，AI 漫剧～～能不能最后成气候，也要看模型最终的能力。但是都逃不脱以上 123 个论据。制造工具平台的，只要不够快吃到第一杯羹或者吃到第一波势头给公司造势拿到投融资之类的，都是死路，只要趋势变了，内容输出平台工具就没意义。","fetched_at":"2026-07-24T14:38:29.202Z","ok":true}