{"id":"56ceee364f8d1436dc0f0c98b8efa76bbf366107","url":"https://www.businessinsider.com/world-cup-technology-referee-camera-offside-microchipped-ball-2026-7","title":"The tech-ification of the World Cup","site_name":"Buzzing","source":"www.businessinsider.com","byline":"Pete Syme","excerpt":"Referees wear a POV camera, there's a sensor in the ball, and all 1,248 players were scanned in 3D.","content_html":"<DIV class=\"page\" id=\"readability-page-1\"><div data-load-strategy=\"disable-lazy\" data-component-type=\"post-top\">\n  \n        \n          \n          \n          \n          \n            <div data-component-type=\"post-byline\" data-track-marfeel=\"post-byline\" data-e2e-name=\"byline\">\n                      <p><span>By</span>\n                              \n                              \n                              \n                                <span data-e2e-name=\"Pete Syme\">\n                              \n                                  <span>\n                                    <a data-e2e-name=\"byline-author-name\" href=\"https://www.businessinsider.com/author/pete-syme\">Pete Syme</a>        \n                                <span data-component-type=\"follow-button\" data-load-strategy=\"lazy\" role=\"tooltip\" data-tooltip-position=\"middle\" data-tooltip-active=\"false\" data-state=\"\" data-topic-type=\"author\" data-topic-slug=\"pete-syme\" data-topic-link=\"https://www.businessinsider.com/author/pete-syme\" data-topic-label=\"Pete Syme\" data-topic-location=\"byline\" data-topic-shortened-label=\"Pete\" data-topic-image=\"{&quot;type&quot;:&quot;image&quot;,&quot;id&quot;:&quot;65201b979f7ca8b2bbdbbf7b&quot;,&quot;attributes&quot;:{&quot;contentType&quot;:&quot;image/png&quot;,&quot;description&quot;:&quot;A headshot of Insider's Pete Syme&quot;,&quot;height&quot;:1860,&quot;source&quot;:&quot;Insider&quot;,&quot;width&quot;:1395},&quot;links&quot;:{&quot;self&quot;:&quot;https://i.insider.com/65201b979f7ca8b2bbdbbf7b&quot;}}\">\n                                  \n                                \n                                  <div>\n                                    <p>\n                                        You're currently following this author!\n                                 Want to unfollow? Unsubscribe via the link in your email.\n                                    </p>\n                                  </div>\n                                  \n                                </span>\n                                  </span>\n                                </span>  </p>\n                    </div>\n      </div><section>\n    \n    \n    \n    \n      <section id=\"post-body\" data-component-type=\"post-body\" data-load-strategy=\"exclude\" data-lock-content=\"\">\n            \n            \n            \n            <div data-component-type=\"post-hero\" data-load-strategy=\"exclude\">\n                  <figure data-type=\"img\" data-e2e-name=\"image-figure-image\" data-media-container=\"image\" itemscope itemtype=\"https://schema.org/ImageObject\">\n                      <div>\n                        <meta itemprop=\"contentUrl\" content=\"https://i.insider.com/6a58cbe8ce52cb26b838fe69?width=1200\">\n                        <p><img src=\"https://i.insider.com/6a58cbe8ce52cb26b838fe69?width=700\" srcset=\"https://i.insider.com/6a58cbe8ce52cb26b838fe69?width=400&format=jpeg&auto=webp 400w, https://i.insider.com/6a58cbe8ce52cb26b838fe69?width=500&format=jpeg&auto=webp 500w, https://i.insider.com/6a58cbe8ce52cb26b838fe69?width=700&format=jpeg&auto=webp 700w, https://i.insider.com/6a58cbe8ce52cb26b838fe69?width=1000&format=jpeg&auto=webp 1000w, https://i.insider.com/6a58cbe8ce52cb26b838fe69?width=1300&format=jpeg&auto=webp 1300w, https://i.insider.com/6a58cbe8ce52cb26b838fe69?width=2000&format=jpeg&auto=webp 2000w\" sizes=\"(min-width: 1280px) 900px\" alt=\"2026 World Cup - France vs. Spain\n                      14 July 2026, United States, Arlington: Soccer, Men: World Cup, France vs. Spain, Final Round, Semifinal, Dallas Stadium. Kylian Mbappé (France) speaks with referee Ivan Barton\" decoding=\"sync\">\n                      </p></div>\n                  \n                    <span>\n                          <span>\n                            \n                            <label for=\"caption-drawer-btn\">\n                                      </label>\n                    \n                            <figcaption data-e2e-name=\"image-caption\">\n                              <span>Referee Ivan Barton speaks to France's Kylian Mbappé during a World Cup semifinal game.</span>\n                              <span>\n                                <span data-e2e-name=\"image-source\" itemprop=\"creditText\">Tom Weller/picture alliance via Getty Images</span>          </span>\n                            </figcaption>\n                          </span>\n                    </span></figure>\n            </div>\n    \n    \n    \n            \n      \n              \n      \n      \n              \n              \n              \n              \n      \n            \n      \n        <section data-load-strategy=\"lazy\" data-component-type=\"image-modal\" data-track-content=\"\" data-post-type=\"story\" data-track-marfeel=\"post-body-content\">\n                  \n                      <p>Tech is playing a bigger role in everyone's lives, and the <a target=\"_self\" href=\"https://www.businessinsider.com/world-cup-so-expensive-5-charts-ticket-prices-hotels-flights-2026-7\" data-track-click=\"{&quot;element_name&quot;:&quot;body_link&quot;,&quot;event&quot;:&quot;tout_click&quot;,&quot;index&quot;:&quot;bi_value_unassigned&quot;,&quot;product_field&quot;:&quot;bi_value_unassigned&quot;}\" rel=\"\">World Cup</a> is no different.</p><p>At the 2026 edition of the tournament — which concludes on Sunday with the final between Argentina and Spain — referees are wearing more equipment than ever before: A camera, a microphone, and two watches. All 1,248 players were scanned in 3D, and the ball contains a microchip.</p><p>Ever since the laws were first codified for the beautiful game, players and fans have argued about referees' decisions. Tech has helped prove incidents one way or another, so refs can make decisions without ambiguity.</p><p>Visualizations and new cameras also give fans more insight into games.</p><p>Here are four key technologies that have played a role in the <a target=\"_self\" href=\"https://www.businessinsider.com/inside-the-cost-of-attending-the-2026-fifa-world-cup-2026-6\" data-track-click=\"{&quot;element_name&quot;:&quot;body_link&quot;,&quot;event&quot;:&quot;tout_click&quot;,&quot;index&quot;:&quot;bi_value_unassigned&quot;,&quot;product_field&quot;:&quot;bi_value_unassigned&quot;}\" rel=\"\">biggest event in sports</a>.</p><h2 id=\"dc020c9c-10d4-4eef-832a-af5c8f38f59c\" data-toc-id=\"dc020c9c-10d4-4eef-832a-af5c8f38f59c\"><strong>Referee View</strong></h2><p>A referee's point-of-view camera lets fans get a closer look at the action on the pitch. From highlighting the difference between a clean tackle and a foul to replays of goals and impressive dribbles to a close-up of a player's remonstrations.</p><p>The Bundesliga, Germany's top league, introduced such a camera in 2024, and other European leagues followed suit — although most only broadcast the images after a game has finished.</p>\n                    \n                  \n                    \n                  <p>For the World Cup, referees wear a headset with a small camera positioned over their ear. The images are shown during the game, with the help of Lenovo, whose AI tech stabilizes the image to reduce motion blur.</p><h2 id=\"ebd42f8a-0139-4351-b56b-d20ae2edd5d9\" data-toc-id=\"ebd42f8a-0139-4351-b56b-d20ae2edd5d9\"><strong>Semi-automated offside</strong></h2><p>Offside is one of the oldest rules in soccer, first codified in 1863, but it relies on fine margins that are hard to judge in real time.</p><p>The law essentially says that an attacker can't be beyond the last defender when the ball is passed to them. It's designed to prevent goalhanging, where a player would loiter near the opponent's goal waiting for an easy chance to score.</p><p>Over the years, there have been too many incidents to name: Goals have been incorrectly disallowed, incorrectly given, or stirred up heated debate. However, there is no arguing with the technology.</p>\n                    <figure data-type=\"img\" data-e2e-name=\"image-figure-image\" data-media-container=\"image\" role=\"button\" tabindex=\"0\" aria-label=\"Click to open image in gallery view\" itemscope itemtype=\"https://schema.org/ImageObject\">\n                    \n                    \n                      <div>\n                  \n                    \n                    <meta itemprop=\"contentUrl\" content=\"https://i.insider.com/6a58c5cc548c9c486b30c96c\">\n                    <p><img data-old-src=\"data:image/svg+xml,%3C%3Fxml version='1.0' encoding='UTF-8'%3F%3E%3Csvg xmlns='http://www.w3.org/2000/svg' width='1' height='1'/%3E\" src=\"https://i.insider.com/6a58c5cc548c9c486b30c96c?width=600&format=jpeg&auto=webp\" alt=\"METLIFE STADIUM, EAST RUTHERFORD, NEW JERSEY, UNITED STATES - 2026/06/30: A giant screen shows a replay highlighting an offside by Kylian Mbappe of France with an on-screen graphic during the FIFA World Cup 2026 round of 32 football match between France and Sweden. France won 3-0 over Sweden.\">\n                      \n                  </p></div>\n                    \n                    <span>\n                          <figcaption data-e2e-name=\"image-caption\">\n                            France's Kylian Mbappé is shown offside by semi-automated offside technology.&#160;\n                            \n                    <span data-e2e-name=\"image-source\" itemprop=\"creditText\">\n                    \n                    Nicolò Campo/LightRocket via Getty Images\n                    \n                    </span>\n                          </figcaption>\n                        </span>\n                    </figure>\n                  <p><a target=\"_self\" href=\"https://www.businessinsider.com/england-premier-league-ai-technology-offside-calls-2024-4\" data-track-click=\"{&quot;element_name&quot;:&quot;body_link&quot;,&quot;event&quot;:&quot;tout_click&quot;,&quot;index&quot;:&quot;bi_value_unassigned&quot;,&quot;product_field&quot;:&quot;bi_value_unassigned&quot;}\" rel=\"\">Semi-automated offside technology</a> uses at least 10 cameras high up in the stadium to track players. AI processes different parts of their bodies and sends an alert if they are offside.</p><p>The World Cup ball also contains a sensor, so the AI knows exactly when the pass was played.</p><p>For this year's tournament, all 1,248 players spent 30 seconds in a 3D scanner to create a unique model, aiding in more precise tracking. Plus, it helps construct a freeze-frame replay of the offside decision.</p>\n                  <h2 id=\"f266e70d-d2d5-49b3-953d-bb0adcbe3f63\" data-toc-id=\"f266e70d-d2d5-49b3-953d-bb0adcbe3f63\"><strong>Snicko</strong></h2><p>The Snickometer, or Snicko, is used to determine whether the ball has made contact with another object or a person. It was first developed for cricket, using a sensitive microphone, but the World Cup uses the sensor in the ball.</p><p>Its most prominent use in the tournament was when Croatia's Joško Gvardiol thought he had rescued a draw against Portugal in added time, but the goal was disallowed.</p><div id=\"1784201652515\" data-styles=\"default-width\" data-embed-type=\"twitter\" data-script=\"https://platform.x.com/widgets.js\" data-type=\"embed\"><blockquote><p lang=\"en\" dir=\"ltr\">According to the data provided by Connected Ball Technology housed within the <a href=\"https://x.com/adidasfootball?ref_src=twsrc%5Etfw\" data-track-click=\"{&quot;click_type&quot;:&quot;other&quot;,&quot;element_name&quot;:&quot;body_link&quot;,&quot;event&quot;:&quot;outbound_click&quot;}\" rel=\" nofollow\" target=\"_blank\">@adidasfootball</a> Trionda, the official match ball of the <a href=\"https://x.com/FIFAWorldCup?ref_src=twsrc%5Etfw\" data-track-click=\"{&quot;click_type&quot;:&quot;other&quot;,&quot;element_name&quot;:&quot;body_link&quot;,&quot;event&quot;:&quot;outbound_click&quot;}\" rel=\" nofollow\" target=\"_blank\">@FIFAWorldCup</a>, it was proven that contact was made by Croatia's #20 Igor Matanović in the build up to the goal against Portugal, allowing the… <a href=\"https://t.co/AyBz11N3wV\" data-track-click=\"{&quot;click_type&quot;:&quot;other&quot;,&quot;element_name&quot;:&quot;body_link&quot;,&quot;event&quot;:&quot;outbound_click&quot;}\" rel=\" nofollow\" target=\"_blank\">pic.twitter.com/AyBz11N3wV</a></p>— FIFA Media (@fifamedia) <a href=\"https://x.com/fifamedia/status/2072879095776764304?ref_src=twsrc%5Etfw\" rel=\" nofollow\" target=\"_blank\">July 3, 2026</a></blockquote>\n                  \n                  \n                  </div><p>At first glance, it looked like the ball was passed straight to a Croatian attacker. However, Snicko showed that another Croatian player headed the ball, at which point his teammate was offside.</p><p>On the other hand, when England equalized against Norway in the quarterfinals, some Norwegian players claimed that England only gained possession because the ball was obstructed by a Spidercam cable above the pitch. Indeed, some pundits questioned the odd trajectory of the kick, but FIFA released a video in which Snicko showed that the ball did not touch anything.</p><h2 id=\"70238795-7ca0-4ad4-b2e8-ff8515d40a95\" data-toc-id=\"70238795-7ca0-4ad4-b2e8-ff8515d40a95\"><strong>Goal-line technology</strong></h2>\n                    <figure data-type=\"img\" data-e2e-name=\"image-figure-image\" data-media-container=\"image\" role=\"button\" tabindex=\"0\" aria-label=\"Click to open image in gallery view\" itemscope itemtype=\"https://schema.org/ImageObject\">\n                    \n                    \n                      <div>\n                  \n                    \n                    <meta itemprop=\"contentUrl\" content=\"https://i.insider.com/6a58c2c0ce52cb26b838fe31\">\n                    <p><img data-old-src=\"data:image/svg+xml,%3C%3Fxml version='1.0' encoding='UTF-8'%3F%3E%3Csvg xmlns='http://www.w3.org/2000/svg' width='1' height='1'/%3E\" src=\"https://i.insider.com/6a58c2c0ce52cb26b838fe31?width=600&format=jpeg&auto=webp\" alt=\"Manuel Neuer of Germany watches the ball bounce over the line from a shot that hit the crossbar from Frank Lampard of England, but referee Jorge Larrionda judges the ball did not cross the line during the 2010 FIFA World Cup\">\n                      \n                  </p></div>\n                    \n                    <span>\n                          <figcaption data-e2e-name=\"image-caption\">\n                            Germany's Manuel Neuer watches the ball bounce over the line after Frank Lampard's shot in 2010.&#160;\n                            \n                    <span data-e2e-name=\"image-source\" itemprop=\"creditText\">\n                    \n                    Cameron Spencer/Getty Images\n                    \n                    </span>\n                          </figcaption>\n                        </span>\n                    </figure>\n                  <p>Seeing the ball ripple the back of the net is a great sight, but sometimes a goal is a scrappier affair. The whole ball has to cross the line to count as a goal, which can be hard for the referee or linesman to see.</p><p>Most infamously, England were knocked out of the 2010 World Cup after a long-range shot from <a target=\"_self\" href=\"https://www.businessinsider.com/frank-lampard-life-retirement-2017-2\" data-track-click=\"{&quot;element_name&quot;:&quot;body_link&quot;,&quot;event&quot;:&quot;tout_click&quot;,&quot;index&quot;:&quot;bi_value_unassigned&quot;,&quot;product_field&quot;:&quot;bi_value_unassigned&quot;}\" rel=\"\">Frank Lampard</a> was incorrectly adjudged not to have crossed the line. The ball went past the German goalkeeper and bounced down off the crossbar into the goal, but the referee waved play on.</p><p>Cue angry headlines from the British press and renewed calls for tech to determine whether the ball has crossed the line.</p><p><a target=\"_self\" href=\"https://www.businessinsider.com/goal-line-technology-may-finally-become-a-reality-today-2012-7\" data-track-click=\"{&quot;element_name&quot;:&quot;body_link&quot;,&quot;event&quot;:&quot;tout_click&quot;,&quot;index&quot;:&quot;bi_value_unassigned&quot;,&quot;product_field&quot;:&quot;bi_value_unassigned&quot;}\" rel=\"\">Goal-line technology</a> was officially approved in 2012, using a similar system to <a target=\"_self\" href=\"https://www.businessinsider.com/tennis-hawk-eye-french-open-umps-judge-by-clay-markings-2020-10\" data-track-click=\"{&quot;element_name&quot;:&quot;body_link&quot;,&quot;event&quot;:&quot;tout_click&quot;,&quot;index&quot;:&quot;bi_value_unassigned&quot;,&quot;product_field&quot;:&quot;bi_value_unassigned&quot;}\" rel=\"\">Hawk-Eye in Tennis</a>. High-speed cameras, focused on the line, can determine whether the ball has crossed it.</p><p>The referee wears a watch that receives the signal within one second.</p>\n                  \n                  \n                  </section>\n    \n    \n    \n    \n      </section>\n\n    \n    <!-- Included desktop \"post-aside\" -->  \n\n    \n      \n      <section data-component-type=\"post-bottom\" data-load-strategy=\"exclude\" data-track-marfeel=\"post-bottom\">\n        <section>\n    \n    \n            \n            \n              \n                \n                \n                <section data-component-type=\"dad-related-posts\" data-delay-third-party-scripts=\"true\" data-size=\"4\" data-min-size=\"3\" data-container-index=\"\" data-included-verticals=\"tech\" data-placement=\"post-bottom\" data-track-marfeel=\"dad-related-posts-post-bottom\" data-excluded-verticals=\"bi-video\" data-root-margin=\"250px 0px\" data-track-view=\"{&quot;element_name&quot;:&quot;end_of_article_recirc&quot;,&quot;product_field&quot;:&quot;bi_value_unassigned&quot;,&quot;subscription_experience&quot;:&quot;bi_value_unassigned&quot;}\">\n                    <P>\n                      <h2>\n                        Read next\n                      </h2>\n                    </P>\n              \n              \n                  \n                </section>\n          \n          \n        <div data-track-click-shared=\"{&quot;product_field&quot;:&quot;bi_value_unassigned&quot;,&quot;element_name&quot;:&quot;author_bio&quot;,&quot;event&quot;:&quot;navigation&quot;}\" data-track-view=\"{&quot;subscription_experience&quot;:&quot;bi_value_unassigned&quot;,&quot;product_field&quot;:&quot;bi_value_unassigned&quot;,&quot;element_name&quot;:&quot;author_bio&quot;,&quot;event&quot;:&quot;module_in_view&quot;}\" data-load-strategy=\"exclude\" data-component-type=\"post-bottom-authors\">\n            <div>\n                <a href=\"https://www.businessinsider.com/author/pete-syme\" data-track-click=\"{&quot;index&quot;:1}\">\n                      <div data-slug=\"pete-syme\">\n                          <p><img data-old-src=\"data:image/svg+xml,%3Csvg xmlns='http://www.w3.org/2000/svg' viewBox='0 0 1 1'%3E%3C/svg%3E\" src=\"https://i.insider.com/65201b979f7ca8b2bbdbbf7b?crop=1:1&width=256&format=jpeg&auto=webp\" alt=\"A headshot of Insider's Pete Syme\">\n                        \n                        \n                        \n                        </p>  </div>\n                </a>\n        \n              <p><a href=\"https://www.businessinsider.com/author/pete-syme\" data-track-click=\"{&quot;index&quot;:1}\">Pete Syme</a>\n        \n                \n          <span data-component-type=\"follow-button\" data-load-strategy=\"lazy\" role=\"tooltip\" data-tooltip-position=\"middle\" data-tooltip-active=\"false\" data-state=\"\" data-topic-type=\"author\" data-topic-slug=\"pete-syme\" data-topic-link=\"https://www.businessinsider.com/author/pete-syme\" data-topic-label=\"Pete Syme\" data-topic-location=\"author_bio\" data-topic-shortened-label=\"Pete\" data-topic-image=\"{&quot;type&quot;:&quot;image&quot;,&quot;id&quot;:&quot;65201b979f7ca8b2bbdbbf7b&quot;,&quot;attributes&quot;:{&quot;contentType&quot;:&quot;image/png&quot;,&quot;description&quot;:&quot;A headshot of Insider's Pete Syme&quot;,&quot;height&quot;:1860,&quot;source&quot;:&quot;Insider&quot;,&quot;width&quot;:1395},&quot;links&quot;:{&quot;self&quot;:&quot;https://i.insider.com/65201b979f7ca8b2bbdbbf7b&quot;}}\">\n            \n          \n            <div>\n              <p>\n                  You're currently following this author!\n           Want to unfollow? Unsubscribe via the link in your email.\n              </p>\n            </div>\n            \n          </span>\n            </p></div>\n        \n            <div>\n              <p><span>Pete Syme is an aviation reporter for Business Insider, based in London.</span><span>He writes about all things related to the industry, such as&#160;<a href=\"https://www.businessinsider.com/15-hour-flight-to-nowhere-iran-strike-qatar-airline-chaos-2025-6\">flight diversions</a>, <a href=\"https://www.businessinsider.com/two-recent-airline-incidents-are-reminder-of-vital-safety-rules-2025-8\">aviation safety</a>, <a href=\"https://www.businessinsider.com/norse-atlantic-airways-cutting-half-its-us-routes-2025-8\">airline updates</a>, <a href=\"https://www.businessinsider.com/british-airways-airbus-a380-economy-window-seat-hack-2025-5\">travel tips</a>,&#160;<a href=\"https://www.businessinsider.com/photos-qatar-airways-boeing-777-psg-inside-the-cockpit-2025-7\">plane tours</a>, and <a href=\"https://www.businessinsider.com/boeing-ceo-kelly-ortberg-one-year-on-turning-around-2025-8\">aviation leaders</a>.</span><span>Pete has appeared on BBC News to discuss a Heathrow Airport closure and on Sky News to talk about Boeing.</span><span>Before joining Business Insider in 2022, he graduated with an MA in Newspaper Journalism from City, University of London. While getting his BA in English from the University of Exeter, he was the award-winning deputy editor of the student newspaper, Exeposé.</span><span>You can get in touch by emailing <a href=\"mailto:psyme@businessinsider.com\">psyme@businessinsider.com</a>&#160;or via Signal @syme.99.</span>\n              </p>\n              </div>\n          </div>\n    \n          \n          \n          \n          <div data-component-type=\"post-category-tags\" data-load-strategy=\"lazy\" data-track-marfeel=\"post-category-tags\">\n            <ul data-track-click-shared=\"{&quot;product_field&quot;:&quot;bi_value_unassigned&quot;,&quot;event&quot;:&quot;navigation&quot;,&quot;element_name&quot;:&quot;category_link&quot;}\">\n                \n                <li>\n                  <a data-track-click=\"\" href=\"/category/world-cup\" title=\"World Cup\">World Cup</a>\n                </li>      \n                <li>\n                  <a data-track-click=\"\" href=\"/category/ai\" title=\"AI\">AI</a>\n                </li>      \n                <li>\n                  <a data-track-click=\"\" href=\"/category/soccer\" title=\"Soccer\">Soccer</a>\n                </li>\n                <li>\n                  <span data-track-click=\"{&quot;click_text&quot;:&quot;More&quot;,&quot;click_path&quot;:&quot;bi_value_unassigned&quot;}\" role=\"button\" tabindex=\"0\">More </span>\n                </li>\n          \n            </ul>\n          </div>\n        </section>\n    \n    \n          <section data-track-page-area=\"Post Bottom\">\n          <!-- Included desktop \"taboola\" -->    <vendor-taboola data-component-type=\"vendor-taboola\" data-root-margin=\"0px 0px 100% 0px\" data-consent=\"MARKETING\" config=\"{&quot;providerName&quot;:&quot;taboola&quot;,&quot;providerPageType&quot;:{&quot;article&quot;:&quot;auto&quot;},&quot;providerUrl&quot;:&quot;https://cdn.taboola.com/libtrc/businessinsider/loader.js&quot;,&quot;providerPrivacyLoader&quot;:&quot;https://static.tblcontent.com/libtrc/businessinsider/loader.privacy.js&quot;,&quot;providerPixel&quot;:&quot;https://static.qovani.com/libtrc/tr5?type=pixel&publisher=businessinsider&quot;,&quot;providerFlushValue&quot;:{&quot;flush&quot;:true},&quot;providerData&quot;:{&quot;mode&quot;:&quot;thumbs-1r&quot;,&quot;container&quot;:&quot;taboola-below-main-column&quot;,&quot;placement&quot;:&quot;below-main-column&quot;,&quot;onlyOn&quot;:&quot;desktop&quot;,&quot;target_type&quot;:&quot;mix&quot;}}\" data-load-strategy=\"defer\">\n                \n              </vendor-taboola>\n          \n          <!-- Excluded mobile \"taboola\" --></section>\n    \n      </section>\n  </section></DIV>","content_text":"By Pete Syme You're currently following this author! Want to unfollow? Unsubscribe via the link in your email. Referee Ivan Barton speaks to France's Kylian Mbappé during a World Cup semifinal game. Tom Weller/picture alliance via Getty Images Tech is playing a bigger role in everyone's lives, and the World Cup is no different.At the 2026 edition of the tournament — which concludes on Sunday with the final between Argentina and Spain — referees are wearing more equipment than ever before: A camera, a microphone, and two watches. All 1,248 players were scanned in 3D, and the ball contains a microchip.Ever since the laws were first codified for the beautiful game, players and fans have argued about referees' decisions. Tech has helped prove incidents one way or another, so refs can make decisions without ambiguity.Visualizations and new cameras also give fans more insight into games.Here are four key technologies that have played a role in the biggest event in sports.Referee ViewA referee's point-of-view camera lets fans get a closer look at the action on the pitch. From highlighting the difference between a clean tackle and a foul to replays of goals and impressive dribbles to a close-up of a player's remonstrations.The Bundesliga, Germany's top league, introduced such a camera in 2024, and other European leagues followed suit — although most only broadcast the images after a game has finished. For the World Cup, referees wear a headset with a small camera positioned over their ear. The images are shown during the game, with the help of Lenovo, whose AI tech stabilizes the image to reduce motion blur.Semi-automated offsideOffside is one of the oldest rules in soccer, first codified in 1863, but it relies on fine margins that are hard to judge in real time.The law essentially says that an attacker can't be beyond the last defender when the ball is passed to them. It's designed to prevent goalhanging, where a player would loiter near the opponent's goal waiting for an easy chance to score.Over the years, there have been too many incidents to name: Goals have been incorrectly disallowed, incorrectly given, or stirred up heated debate. However, there is no arguing with the technology. France's Kylian Mbappé is shown offside by semi-automated offside technology. Nicolò Campo/LightRocket via Getty Images Semi-automated offside technology uses at least 10 cameras high up in the stadium to track players. AI processes different parts of their bodies and sends an alert if they are offside.The World Cup ball also contains a sensor, so the AI knows exactly when the pass was played.For this year's tournament, all 1,248 players spent 30 seconds in a 3D scanner to create a unique model, aiding in more precise tracking. Plus, it helps construct a freeze-frame replay of the offside decision. SnickoThe Snickometer, or Snicko, is used to determine whether the ball has made contact with another object or a person. It was first developed for cricket, using a sensitive microphone, but the World Cup uses the sensor in the ball.Its most prominent use in the tournament was when Croatia's Joško Gvardiol thought he had rescued a draw against Portugal in added time, but the goal was disallowed.According to the data provided by Connected Ball Technology housed within the @adidasfootball Trionda, the official match ball of the @FIFAWorldCup, it was proven that contact was made by Croatia's #20 Igor Matanović in the build up to the goal against Portugal, allowing the… pic.twitter.com/AyBz11N3wV— FIFA Media (@fifamedia) July 3, 2026 At first glance, it looked like the ball was passed straight to a Croatian attacker. However, Snicko showed that another Croatian player headed the ball, at which point his teammate was offside.On the other hand, when England equalized against Norway in the quarterfinals, some Norwegian players claimed that England only gained possession because the ball was obstructed by a Spidercam cable above the pitch. Indeed, some pundits questioned the odd trajectory of the kick, but FIFA released a video in which Snicko showed that the ball did not touch anything.Goal-line technology Germany's Manuel Neuer watches the ball bounce over the line after Frank Lampard's shot in 2010. Cameron Spencer/Getty Images Seeing the ball ripple the back of the net is a great sight, but sometimes a goal is a scrappier affair. The whole ball has to cross the line to count as a goal, which can be hard for the referee or linesman to see.Most infamously, England were knocked out of the 2010 World Cup after a long-range shot from Frank Lampard was incorrectly adjudged not to have crossed the line. The ball went past the German goalkeeper and bounced down off the crossbar into the goal, but the referee waved play on.Cue angry headlines from the British press and renewed calls for tech to determine whether the ball has crossed the line.Goal-line technology was officially approved in 2012, using a similar system to Hawk-Eye in Tennis. High-speed cameras, focused on the line, can determine whether the ball has crossed it.The referee wears a watch that receives the signal within one second. Read next Pete Syme You're currently following this author! Want to unfollow? Unsubscribe via the link in your email. Pete Syme is an aviation reporter for Business Insider, based in London.He writes about all things related to the industry, such as flight diversions, aviation safety, airline updates, travel tips, plane tours, and aviation leaders.Pete has appeared on BBC News to discuss a Heathrow Airport closure and on Sky News to talk about Boeing.Before joining Business Insider in 2022, he graduated with an MA in Newspaper Journalism from City, University of London. While getting his BA in English from the University of Exeter, he was the award-winning deputy editor of the student newspaper, Exeposé.You can get in touch by emailing psyme@businessinsider.com or via Signal @syme.99. World Cup AI Soccer More","fetched_at":"2026-07-19T10:33:43.239Z","ok":true,"content_html_zh":"<div class=\"page\" id=\"readability-page-1\"><div data-load-strategy=\"disable-lazy\" data-component-type=\"post-top\">\n  \n        \n          \n          \n          \n          \n            <div data-component-type=\"post-byline\" data-track-marfeel=\"post-byline\" data-e2e-name=\"byline\">\n                      <p>作者：Pete Syme 您目前正在关注该作者！想要取消关注吗？通过电子邮件中的链接取消订阅。</p>\n                    </div>\n      </div><section>\n    \n    \n    \n    \n      <section id=\"post-body\" data-component-type=\"post-body\" data-load-strategy=\"exclude\" data-lock-content=\"\">\n            \n            \n            \n            <div data-component-type=\"post-hero\" data-load-strategy=\"exclude\">\n                  <figure data-type=\"img\" data-e2e-name=\"image-figure-image\" data-media-container=\"image\" itemscope itemtype=\"https://schema.org/ImageObject\">\n                      <div>\n                        <meta itemprop=\"contentUrl\" content=\"https://i.insider.com/6a58cbe8ce52cb26b838fe69?width=1200\">\n                        <p><img src=\"https://i.insider.com/6a58cbe8ce52cb26b838fe69?width=700\" srcset=\"https://i.insider.com/6a58cbe8ce52cb26b838fe69?width=400&format=jpeg&auto=webp 400w, https://i.insider.com/6a58cbe8ce52cb26b838fe69?width=500&format=jpeg&auto=webp 500w, https://i.insider.com/6a58cbe8ce52cb26b838fe69?width=700&format=jpeg&auto=webp 700w, https://i.insider.com/6a58cbe8ce52cb26b838fe69?width=1000&format=jpeg&auto=webp 1000w, https://i.insider.com/6a58cbe8ce52cb26b838fe69?width=1300&format=jpeg&auto=webp 1300w, https://i.insider.com/6a58cbe8ce52cb26b838fe69?width=2000&format=jpeg&auto=webp 2000w\" sizes=\"(min-width: 1280px) 900px\" alt=\"2026 World Cup - France vs. Spain\n                      14 July 2026, United States, Arlington: Soccer, Men: World Cup, France vs. Spain, Final Round, Semifinal, Dallas Stadium. Kylian Mbappé (France) speaks with referee Ivan Barton\" decoding=\"sync\">\n                      </p></div>\n                  \n                    <span>\n                          <span>\n                            \n                            <label for=\"caption-drawer-btn\">\n                                      </label>\n                    \n                            <figcaption data-e2e-name=\"image-caption\">裁判伊万·巴顿在世界杯半决赛中与法国队球员基利安·姆巴佩交谈。汤姆·韦勒/图片联盟来自盖蒂图片社</figcaption>\n                          </span>\n                    </span></figure>\n            </div>\n    \n    \n    \n            \n      \n              \n      \n      \n              \n              \n              \n              \n      \n            \n      \n        <section data-load-strategy=\"lazy\" data-component-type=\"image-modal\" data-track-content=\"\" data-post-type=\"story\" data-track-marfeel=\"post-body-content\">\n                  \n                      <p>科技在每个人的生活中发挥着越来越重要的作用，世界杯也不例外。</p><p>2026 年世界杯将于周日在阿根廷和西班牙之间进行决赛，裁判们佩戴的设备比以往更多：一台摄像机、一个麦克风和两块手表。所有 1,248 名球员都经过 3D 扫描，并且球中含有微芯片。</p><p>自从这项美丽的比赛的法律首次被制定以来，球员和球迷就一直对裁判的决定争论不休。技术以某种方式帮助证明事件，因此裁判可以毫不含糊地做出决定。</p><p>可视化和新摄像头也让球迷更深入地了解比赛。</p><p>以下是在最大的体育赛事中发挥作用的四项关键技术。</p><h2 id=\"dc020c9c-10d4-4eef-832a-af5c8f38f59c\" data-toc-id=\"dc020c9c-10d4-4eef-832a-af5c8f38f59c\">裁判视图</h2><p>裁判的视点摄像机可以让球迷近距离观察球场上的动作。从强调干净铲球和犯规之间的区别，到进球重播和令人印象深刻的运球，再到球员抗议的特写镜头。</p><p>德国顶级联赛德甲联赛于 2024 年引入了此类摄像机，其他欧洲联赛也纷纷效仿，尽管大多数联赛仅在比赛结束后转播图像。</p>\n                    \n                  \n                    \n                  <p>在世界杯上，裁判们戴着耳机，耳朵上有一个小型摄像头。这些图像是在联想的帮助下在游戏过程中显示的，联想的人工智能技术可以稳定图像以减少运动模糊。</p><h2 id=\"ebd42f8a-0139-4351-b56b-d20ae2edd5d9\" data-toc-id=\"ebd42f8a-0139-4351-b56b-d20ae2edd5d9\">半自动越位</h2><p>越位是足球界最古老的规则之一，于 1863 年首次制定，但它依赖于难以实时判断的细微差别。</p><p>法律本质上规定，当球传给进攻者时，进攻者不能超越最后一名防守者。它的设计目的是为了防止挂球，即球员在对手球门附近徘徊，等待轻松得分的机会。</p><p>多年来，发生了太多的事件：被错误地拒绝、错误地给出目标或引发激烈的争论。然而，这项技术是无可争议的。</p>\n                    <figure data-type=\"img\" data-e2e-name=\"image-figure-image\" data-media-container=\"image\" role=\"button\" tabindex=\"0\" aria-label=\"Click to open image in gallery view\" itemscope itemtype=\"https://schema.org/ImageObject\">\n                    \n                    \n                      <div>\n                  \n                    \n                    <meta itemprop=\"contentUrl\" content=\"https://i.insider.com/6a58c5cc548c9c486b30c96c\">\n                    <p><img data-old-src=\"data:image/svg+xml,%3C%3Fxml version='1.0' encoding='UTF-8'%3F%3E%3Csvg xmlns='http://www.w3.org/2000/svg' width='1' height='1'/%3E\" src=\"https://i.insider.com/6a58c5cc548c9c486b30c96c?width=600&format=jpeg&auto=webp\" alt=\"METLIFE STADIUM, EAST RUTHERFORD, NEW JERSEY, UNITED STATES - 2026/06/30: A giant screen shows a replay highlighting an offside by Kylian Mbappe of France with an on-screen graphic during the FIFA World Cup 2026 round of 32 football match between France and Sweden. France won 3-0 over Sweden.\">\n                      \n                  </p></div>\n                    \n                    <span>\n                          <figcaption data-e2e-name=\"image-caption\">法国队的基利安·姆巴佩通过半自动越位技术被判越位。 Nicolò Campo/LightRocket 来自 Getty Images</figcaption>\n                        </span>\n                    </figure>\n                  <p>半自动越位技术使用体育场高处至少 10 个摄像头来跟踪球员。人工智能会处理他们身体的不同部位，并在他们越位时发出警报。</p><p>世界杯用球还包含一个传感器，因此人工智能可以准确地知道传球的时间。</p><p>在今年的比赛中，所有 1,248 名选手在 3D 扫描仪中花了 30 秒来创建一个独特的模型，以帮助更精确的跟踪。此外，它还有助于构建越位决定的定格回放。</p>\n                  <h2 id=\"f266e70d-d2d5-49b3-953d-bb0adcbe3f63\" data-toc-id=\"f266e70d-d2d5-49b3-953d-bb0adcbe3f63\">斯尼科</h2><p>Snickometer（或 Snicko）用于确定球是否与其他物体或人接触。它最初是为板球运动开发的，使用灵敏的麦克风，但世界杯则使用球内的传感器。</p><p>它在世界杯上最突出的用途是克罗地亚队的约什科·格瓦尔迪奥尔（Joško Gvardiol）认为他在补时阶段挽救了与葡萄牙队的平局，但该进球被判无效。</p><div id=\"1784201652515\" data-styles=\"default-width\" data-embed-type=\"twitter\" data-script=\"https://platform.x.com/widgets.js\" data-type=\"embed\"><blockquote>根据@adidasfootball Trionda（@FIFAWorldCup 的官方比赛用球）内的 Connected Ball Technology 提供的数据，事实证明，克罗地亚队的 20 号伊戈尔·马塔诺维奇 (Igor Matanović) 在对阵葡萄牙的进球前发生了接触，从而允许…… pic.twitter.com/AyBz11N3wV — FIFA Media (@fifamedia) 2026 年 7 月 3 日</blockquote>\n                  \n                  \n                  </div><p>乍一看，球像是直接传给了克罗地亚前锋。然而，斯尼科展示了另一名克罗地亚球员的头球，此时他的队友已经越位。</p><p>另一方面，当英格兰在四分之一决赛中与挪威扳平比分时，一些挪威球员声称英格兰只是因为球被球场上方的蜘蛛摄像机电缆阻挡而获得控球权。事实上，一些专家质疑踢球的奇怪轨迹，但国际足联发布了一段视频，其中斯尼科显示球没有接触到任何东西。</p><h2 id=\"70238795-7ca0-4ad4-b2e8-ff8515d40a95\" data-toc-id=\"70238795-7ca0-4ad4-b2e8-ff8515d40a95\">门线技术</h2>\n                    <figure data-type=\"img\" data-e2e-name=\"image-figure-image\" data-media-container=\"image\" role=\"button\" tabindex=\"0\" aria-label=\"Click to open image in gallery view\" itemscope itemtype=\"https://schema.org/ImageObject\">\n                    \n                    \n                      <div>\n                  \n                    \n                    <meta itemprop=\"contentUrl\" content=\"https://i.insider.com/6a58c2c0ce52cb26b838fe31\">\n                    <p><img data-old-src=\"data:image/svg+xml,%3C%3Fxml version='1.0' encoding='UTF-8'%3F%3E%3Csvg xmlns='http://www.w3.org/2000/svg' width='1' height='1'/%3E\" src=\"https://i.insider.com/6a58c2c0ce52cb26b838fe31?width=600&format=jpeg&auto=webp\" alt=\"Manuel Neuer of Germany watches the ball bounce over the line from a shot that hit the crossbar from Frank Lampard of England, but referee Jorge Larrionda judges the ball did not cross the line during the 2010 FIFA World Cup\">\n                      \n                  </p></div>\n                    \n                    <span>\n                          <figcaption data-e2e-name=\"image-caption\">2010 年弗兰克·兰帕德射门后，德国队的曼努埃尔·诺伊尔看着球弹过底线。卡梅伦·斯宾塞/盖蒂图片社</figcaption>\n                        </span>\n                    </figure>\n                  <p>看到球在网后荡漾是一种美妙的景象，但有时进球是一件更斗志旺盛的事情。整个球必须越过球门线才算进球，这对于裁判员或边裁来说很难看到。</p><p>最臭名昭著的是，英格兰在2010年世界杯上被淘汰出局，原因是弗兰克·兰帕德的远射被错误地判定为没有越过球门线。球越过了德国守门员，从横梁上弹回球门，但裁判挥手示意继续比赛。</p><p>英国媒体报道了愤怒的头条新闻，并再次呼吁利用技术来确定球是否越界。</p><p>门线技术于 2012 年获得正式批准，使用与网球中的鹰眼系统类似的系统。聚焦在球线上的高速摄像机可以确定球是否越过球线。</p><p>裁判佩戴的手表可以在一秒钟内接收到信号。</p>\n                  \n                  \n                  </section>\n    \n    \n    \n    \n      </section>\n\n    \n    <!-- Included desktop \"post-aside\" -->  \n\n    \n      \n      <section data-component-type=\"post-bottom\" data-load-strategy=\"exclude\" data-track-marfeel=\"post-bottom\">\n        <section>\n    \n    \n            \n            \n              \n                \n                \n                <section data-component-type=\"dad-related-posts\" data-delay-third-party-scripts=\"true\" data-size=\"4\" data-min-size=\"3\" data-container-index=\"\" data-included-verticals=\"tech\" data-placement=\"post-bottom\" data-track-marfeel=\"dad-related-posts-post-bottom\" data-excluded-verticals=\"bi-video\" data-root-margin=\"250px 0px\" data-track-view=\"{&quot;element_name&quot;:&quot;end_of_article_recirc&quot;,&quot;product_field&quot;:&quot;bi_value_unassigned&quot;,&quot;subscription_experience&quot;:&quot;bi_value_unassigned&quot;}\">\n                    <p>\n                      </p><h2>阅读下一篇</h2>\n                    <p></p>\n              \n              \n                  \n                </section>\n          \n          \n        <div data-track-click-shared=\"{&quot;product_field&quot;:&quot;bi_value_unassigned&quot;,&quot;element_name&quot;:&quot;author_bio&quot;,&quot;event&quot;:&quot;navigation&quot;}\" data-track-view=\"{&quot;subscription_experience&quot;:&quot;bi_value_unassigned&quot;,&quot;product_field&quot;:&quot;bi_value_unassigned&quot;,&quot;element_name&quot;:&quot;author_bio&quot;,&quot;event&quot;:&quot;module_in_view&quot;}\" data-load-strategy=\"exclude\" data-component-type=\"post-bottom-authors\">\n            <div>\n                <a href=\"https://www.businessinsider.com/author/pete-syme\" data-track-click=\"{&quot;index&quot;:1}\">\n                      <div data-slug=\"pete-syme\">\n                          <p><img data-old-src=\"data:image/svg+xml,%3Csvg xmlns='http://www.w3.org/2000/svg' viewBox='0 0 1 1'%3E%3C/svg%3E\" src=\"https://i.insider.com/65201b979f7ca8b2bbdbbf7b?crop=1:1&width=256&format=jpeg&auto=webp\" alt=\"A headshot of Insider's Pete Syme\">\n                        \n                        \n                        \n                        </p>  </div>\n                </a>\n        \n              <p>Pete Syme 您目前正在关注该作者！想要取消关注吗？通过电子邮件中的链接取消订阅。</p></div>\n        \n            <div>\n              <p>皮特·赛姆 (Pete Syme) 是《商业内幕》驻伦敦的航空记者。他撰写与该行业相关的所有内容，例如航班改道、航空安全、航空公司更新、旅行提示、飞机旅行和航空领导者。皮特曾在 BBC 新闻中讨论希思罗机场关闭问题，在天空新闻中谈论波音。在 2022 年加入《商业内幕》之前，他毕业于伦敦城市大学报纸新闻学硕士学位。在埃克塞特大学获得英语学士学位时，他是学生报纸 Exeposé 的获奖副主编。您可以通过发送电子邮件至 psyme@businessinsider.com 或通过 Signal @syme.99 与我们联系。</p>\n              </div>\n          </div>\n    \n          \n          \n          \n          <div data-component-type=\"post-category-tags\" data-load-strategy=\"lazy\" data-track-marfeel=\"post-category-tags\">\n            <ul data-track-click-shared=\"{&quot;product_field&quot;:&quot;bi_value_unassigned&quot;,&quot;event&quot;:&quot;navigation&quot;,&quot;element_name&quot;:&quot;category_link&quot;}\">\n                \n                <li>世界杯</li>      \n                <li>\n                  <a data-track-click=\"\" href=\"/category/ai\" title=\"AI\">AI</a>\n                </li>      \n                <li>足球</li>\n                <li>\n                  <span data-track-click=\"{&quot;click_text&quot;:&quot;More&quot;,&quot;click_path&quot;:&quot;bi_value_unassigned&quot;}\" role=\"button\" tabindex=\"0\">More </span>\n                </li>\n          \n            </ul>\n          </div>\n        </section>\n    \n    \n          <section data-track-page-area=\"Post Bottom\">\n          <!-- Included desktop \"taboola\" -->    <vendor-taboola data-component-type=\"vendor-taboola\" data-root-margin=\"0px 0px 100% 0px\" data-consent=\"MARKETING\" config=\"{&quot;providerName&quot;:&quot;taboola&quot;,&quot;providerPageType&quot;:{&quot;article&quot;:&quot;auto&quot;},&quot;providerUrl&quot;:&quot;https://cdn.taboola.com/libtrc/businessinsider/loader.js&quot;,&quot;providerPrivacyLoader&quot;:&quot;https://static.tblcontent.com/libtrc/businessinsider/loader.privacy.js&quot;,&quot;providerPixel&quot;:&quot;https://static.qovani.com/libtrc/tr5?type=pixel&publisher=businessinsider&quot;,&quot;providerFlushValue&quot;:{&quot;flush&quot;:true},&quot;providerData&quot;:{&quot;mode&quot;:&quot;thumbs-1r&quot;,&quot;container&quot;:&quot;taboola-below-main-column&quot;,&quot;placement&quot;:&quot;below-main-column&quot;,&quot;onlyOn&quot;:&quot;desktop&quot;,&quot;target_type&quot;:&quot;mix&quot;}}\" data-load-strategy=\"defer\">\n                \n              </vendor-taboola>\n          \n          <!-- Excluded mobile \"taboola\" --></section>\n    \n      </section>\n  </section></div>","translated":true}