{"id":"6113c3220e449d125c55663e5c4030b4b97e9589","url":"https://36kr.com/newsflashes/3907683274675337?f=rss","title":"阅文推出文创AI智能体“Buddy系列”-36氪","site_name":"Info Flow","source":"36氪 (36Kr)","byline":null,"excerpt":"36氪获悉，近日，阅文集团发布文创垂直AI智能体Buddy系列，升级作家助手NovelBuddy、漫剧助手DramaBuddy、版权助手IPBuddy三款产品，形成覆盖内容创作、IP改编、版权开发的一体化AI工具矩阵。","content_html":"<DIV class=\"page\" id=\"readability-page-1\"><div><div><div><p><span>2026-07-23 11:40</span><span>分享至</span></p></div><div><pre>36氪获悉，近日，阅文集团发布文创垂直AI智能体Buddy系列，升级作家助手NovelBuddy、漫剧助手DramaBuddy、版权助手IPBuddy三款产品，形成覆盖内容创作、IP改编、版权开发的一体化AI工具矩阵。</pre></div></div><div><p>36氪获悉，天眼查App显示，近日，苏州乐享智能科技有限公司近日发生工商变更，新增蚂蚁集团旗下上海云玚企业管理咨询有限公司、安徽泰运投资管理有限公司等为股东，同时，注册资本由约196.5万人民币增至约217.3万人民币。该公司成立于2024年12月，法定代表人为郭人杰，经营范围包括智能机器人的研发、人工智能应用软件开发等，现由郭人杰、苏州凌码科技合伙企业及上述新增股东等共同持股。</p><p>23小时前</p></div></div></DIV>","content_text":"2026-07-23 11:40分享至36氪获悉，近日，阅文集团发布文创垂直AI智能体Buddy系列，升级作家助手NovelBuddy、漫剧助手DramaBuddy、版权助手IPBuddy三款产品，形成覆盖内容创作、IP改编、版权开发的一体化AI工具矩阵。36氪获悉，天眼查App显示，近日，苏州乐享智能科技有限公司近日发生工商变更，新增蚂蚁集团旗下上海云玚企业管理咨询有限公司、安徽泰运投资管理有限公司等为股东，同时，注册资本由约196.5万人民币增至约217.3万人民币。该公司成立于2024年12月，法定代表人为郭人杰，经营范围包括智能机器人的研发、人工智能应用软件开发等，现由郭人杰、苏州凌码科技合伙企业及上述新增股东等共同持股。23小时前","fetched_at":"2026-07-24T03:08:25.676Z","ok":true}