{"id":"bfde6fbc5a70cbc5dc7c8d890507f2f39a766b21","url":"https://www.huxiu.com/article/4876172.html?f=rss","title":"AI算力群的“群聊”基建，为什么是中国公司承包了？","site_name":"Info Flow","source":"虎嗅 (Huxiu)","byline":"金角财经","excerpt":"中国高端制造已经站上AI核心链","content_html":"<DIV class=\"page\" id=\"readability-page-1\"><div data-v-42acfa7d=\"\"><div id=\"js-article-read-wrap\" data-v-42acfa7d=\"\"><!----><!----><p><span data-v-42acfa7d=\"\">2026-07-20 11:22</span></p><div data-v-42acfa7d=\"\"><p><a href=\"https://www.huxiu.com/member/3116337.html\" target=\"_blank\" data-v-42acfa7d=\"\"><span data-v-42acfa7d=\"\">金角财经</span><span data-v-42acfa7d=\"\" data-v-dfc547f0=\"\"><!--[--><img src=\"https://img.huxiucdn.com/icon/author_4.png\" alt=\"认证作者 Lv.4\" title=\"认证作者 Lv.4\" data-v-dfc547f0=\"\"><img src=\"https://img.huxiucdn.com/auth/data/user_icons/bi_hu_xiao_dui.png\" alt=\"壁虎小队\" title=\"壁虎小队\" data-v-dfc547f0=\"\"><!--]--></span></a></p></div><!----><div data-v-42acfa7d=\"\"><p><span data-v-42acfa7d=\"\">内容为转载</span><span data-v-42acfa7d=\"\"> #高新技术流</span></p></div><div data-v-42acfa7d=\"\"><p data-check-id=\"612050\">A股的光模块板块疯涨，业绩同样猛，比如中际旭创一季度营收同比涨了192%，背后是全球AI数据中心的实打实订单。</p></div></div><div data-v-42acfa7d=\"\"><!----><p><a target=\"_blank\" href=\"/channel/10\" data-v-42acfa7d=\"\">频道: 视频</a></p></div><!--[--><div data-v-42acfa7d=\"\"><a href=\"/member/3116337.html\" target=\"_blank\" data-v-42acfa7d=\"\" data-v-7b99ddca=\"\"><div data-v-7b99ddca=\"\"><div data-v-7b99ddca=\"\"><p data-v-7b99ddca=\"\">金角财经</p><p data-v-7b99ddca=\"\">城市新中产读本，拆解经济事件背</p></div><div data-v-7b99ddca=\"\"><p data-v-7b99ddca=\"\">认证作者</p><p data-v-7b99ddca=\"\"> 已在虎嗅发表 <span data-v-7b99ddca=\"\">206</span> 篇文章 </p></div></div></a></div><div data-v-42acfa7d=\"\"><p>本内容由作者授权发布，观点仅代表作者本人，不代表虎嗅立场。<br>如对本稿件有异议或投诉，请联系 tougao@huxiu.com。</p><p>正在改变与想要改变世界的人，都在<a href=\"https://www.huxiu.com/app.html\" target=\"_blank\"> 虎嗅APP<span></span></a></p></div><!--]--></div></DIV>","content_text":"2026-07-20 11:22金角财经内容为转载 #高新技术流A股的光模块板块疯涨，业绩同样猛，比如中际旭创一季度营收同比涨了192%，背后是全球AI数据中心的实打实订单。频道: 视频金角财经城市新中产读本，拆解经济事件背认证作者 已在虎嗅发表 206 篇文章 本内容由作者授权发布，观点仅代表作者本人，不代表虎嗅立场。如对本稿件有异议或投诉，请联系 tougao@huxiu.com。正在改变与想要改变世界的人，都在 虎嗅APP","fetched_at":"2026-07-21T03:08:38.041Z","ok":true}