{"id":"e40135c5a3bf48f6ee809b7323e58b402ef5e8f9","url":"https://www.ithome.com/0/981/386.htm","title":"微星发布 4L 紧凑型台式机 PRO MAX EDGE AI+，基于 AMD 锐龙 AI Max+ 300","site_name":"Info Flow","source":"IT之家 (ITHome)","byline":"作者：溯波（实习）","excerpt":"其单机支持 120B 模型本地运行，在 109B 模型上拥有 15 Token/s 的推理输出吞吐量；多机 USB4 互连后可处理 670B 模型。","content_html":"<DIV class=\"page\" id=\"readability-page-1\"><div id=\"paragraph\">\r\n            \r\n            <p data-vmark=\"a961\"><a href=\"https://www.ithome.com/\" target=\"_blank\">IT之家</a> 7 月 24 日消息，微星 (MSI) 今日宣布推出基于 AMD 锐龙 AI Max+ 300 处理器的 4L 紧凑型台式机系统 <strong>PRO MAX EDGE AI+</strong>。</p><p data-vmark=\"d0d3\"><img src=\"https://img.ithome.com/newsuploadfiles/2026/7/13ec1b86-95ae-4a7e-af64-89fb7b50a6f8.jpg@s_2,w_820,h_342\" w=\"960\" h=\"400\" data-vmark=\"42b3\" title=\"微星发布 4L 紧凑型台式机 PRO MAX EDGE AI+，基于 AMD 锐龙 AI Max+ 300\" srcset=\"https://img.ithome.com/newsuploadfiles/2026/7/13ec1b86-95ae-4a7e-af64-89fb7b50a6f8.jpg 2x\" data-original=\"https://img.ithome.com/newsuploadfiles/2026/7/13ec1b86-95ae-4a7e-af64-89fb7b50a6f8.jpg@s_2,w_820,h_342\" width=\"960\" height=\"342\"></p><p data-vmark=\"5a42\">这一产品采用内置 Flex ATX 电源设计，配备 3 热管 3 风扇散热系统；<strong>支持至高 128GB 容量的 256-bit 8000MT/s LPDDR5X 内存</strong>，提供 2 个 M.2 PCIe Gen4 ×4 NVMe SSD 盘位；预装 AMD RZ717 无线网卡（支持 Wi-Fi 7）。</p><p data-vmark=\"4026\">外部 I/O 方面，其正面拥有 1 个 USB-C 40Gbps、2 个 USB-A 10Gbps、1 个 3.5mm 二合一音频插孔、1 个 UHS-II SD 读卡器；反面包括 1 个 USB-C 40Gbps、1 个 USB-A 10Gbps、2 个 USB-A 480Mbps、1 个 2.5GbE RJ45、1 个 HDMI 2.1 TMDS、1 个 DisplayPort 1.4a、1 个 3.5mm 二合一音频插孔。</p><p data-vmark=\"e397\"><img src=\"https://img.ithome.com/newsuploadfiles/2026/7/1014bd5e-8b8e-4b40-bbce-de9c613b829b.png\" w=\"1440\" h=\"1152\" data-vmark=\"0730\" title=\"微星发布 4L 紧凑型台式机 PRO MAX EDGE AI+，基于 AMD 锐龙 AI Max+ 300\" data-original=\"https://img.ithome.com/newsuploadfiles/2026/7/1014bd5e-8b8e-4b40-bbce-de9c613b829b.png\" width=\"1440\" height=\"656\"></p><p data-vmark=\"a640\">PRO MAX EDGE AI+ 单机支持 120B 模型本地运行，<strong>在 109B 模型上拥有 15 Token/s 的推理输出吞吐量</strong>；多机 USB4 互连后可处理 670B 模型。</p><p>广告声明：文内含有的对外跳转链接（包括不限于超链接、二维码、口令等形式），用于传递更多信息，节省甄选时间，结果仅供参考，IT之家所有文章均包含本声明。</p>\r\n        </div></DIV>","content_text":"IT之家 7 月 24 日消息，微星 (MSI) 今日宣布推出基于 AMD 锐龙 AI Max+ 300 处理器的 4L 紧凑型台式机系统 PRO MAX EDGE AI+。这一产品采用内置 Flex ATX 电源设计，配备 3 热管 3 风扇散热系统；支持至高 128GB 容量的 256-bit 8000MT/s LPDDR5X 内存，提供 2 个 M.2 PCIe Gen4 ×4 NVMe SSD 盘位；预装 AMD RZ717 无线网卡（支持 Wi-Fi 7）。外部 I/O 方面，其正面拥有 1 个 USB-C 40Gbps、2 个 USB-A 10Gbps、1 个 3.5mm 二合一音频插孔、1 个 UHS-II SD 读卡器；反面包括 1 个 USB-C 40Gbps、1 个 USB-A 10Gbps、2 个 USB-A 480Mbps、1 个 2.5GbE RJ45、1 个 HDMI 2.1 TMDS、1 个 DisplayPort 1.4a、1 个 3.5mm 二合一音频插孔。PRO MAX EDGE AI+ 单机支持 120B 模型本地运行，在 109B 模型上拥有 15 Token/s 的推理输出吞吐量；多机 USB4 互连后可处理 670B 模型。广告声明：文内含有的对外跳转链接（包括不限于超链接、二维码、口令等形式），用于传递更多信息，节省甄选时间，结果仅供参考，IT之家所有文章均包含本声明。","fetched_at":"2026-07-24T14:38:02.878Z","ok":true}